pyrdmdl/__init__.py
pyrdmdl/glm.py
pyrdmdl/lm.py
pyrdmdl/pca.py
pyrdmdl-1.0.2.dist-info/LICENSE
pyrdmdl-1.0.2.dist-info/METADATA
pyrdmdl-1.0.2.dist-info/WHEEL
pyrdmdl-1.0.2.dist-info/top_level.txt
pyrdmdl-1.0.2.dist-info/RECORD
